[
  {
    "domain": ".facebook.com",
    "httpOnly": false,
    "name": "presence",
    "path": "/",
    "sameSite": "Lax",
    "secure": true,
    "value": "C%7B%22t3%22%3A%5B%5D%2C%22utc3%22%3A1761548619124%2C%22v%22%3A1%7D"
  },
  {
    "domain": ".facebook.com",
    "expiry": 1769324615,
    "httpOnly": true,
    "name": "fr",
    "path": "/",
    "sameSite": "None",
    "secure": true,
    "value": "0V0bZVXiuHpa3S9qZ.AWf0S2us9CEIj-L9X6kuw2tCNyK-rfDQyUoepdyB4YwlZevq2JU.Bo_xk2..AAA.0.0.Bo_xlH.AWc0gIbnGfHUuSGM6OS9VnQuOOc"
  },
  {
    "domain": ".facebook.com",
    "expiry": 1793084615,
    "httpOnly": true,
    "name": "xs",
    "path": "/",
    "sameSite": "None",
    "secure": true,
    "value": "33%3AMZnPU3ByE8j7TA%3A2%3A1761548613%3A-1%3A-1"
  },
  {
    "domain": ".facebook.com",
    "expiry": 1762153417,
    "httpOnly": false,
    "name": "wd",
    "path": "/",
    "sameSite": "Lax",
    "secure": true,
    "value": "1036x651"
  },
  {
    "domain": ".facebook.com",
    "expiry": 1793084615,
    "httpOnly": false,
    "name": "c_user",
    "path": "/",
    "sameSite": "None",
    "secure": true,
    "value": "61578570012405"
  },
  {
    "domain": ".facebook.com",
    "expiry": 1762153417,
    "httpOnly": false,
    "name": "dpr",
    "path": "/",
    "sameSite": "None",
    "secure": true,
    "value": "1.25"
  },
  {
    "domain": ".facebook.com",
    "expiry": 1796108615,
    "httpOnly": true,
    "name": "sb",
    "path": "/",
    "sameSite": "None",
    "secure": true,
    "value": "Nhn_aAW87ycN3C9RQ9Wg7nyL"
  },
  {
    "domain": ".facebook.com",
    "expiry": 1796108599,
    "httpOnly": true,
    "name": "datr",
    "path": "/",
    "sameSite": "None",
    "secure": true,
    "value": "Nhn_aKgt5tEs2vtQwq6gjXlz"
  }
]